spiro/automl/model_assembler.py
spiro/automl/tf/batch_training.py
spiro/automl/tf/model_assembler_tf.py
spiro/automl/tf/prepare_dataset.py
spiro/automl/tf/sampler.py
spiro/automl/torch/model_assembler_torch.py
spiro/core/__init__.py
spiro/core/backend_config/tensorflow.py
spiro/core/backend_config/torch.py
spiro/core/backends.py
spiro/core/commonF.py
spiro/core/config.py
spiro/core/dataio.py
spiro/core/errors.py
spiro/core/layers.py
spiro/core/logger.py
spiro/core/tf/conv1D.py
spiro/core/tf/structualAttention.py
spiro/core/tf/time2Vec.py
spiro/core/tf/tsa.py
spiro/core/tf_functions.py
spiro/core/torch_functions.py
spiro/core/types.py
spiro/core/utils.py
spiro/dtdg/__init__.py
spiro/dtdg/dataloader.py
spiro/dtdg/models/decoder/__init__.py
spiro/dtdg/models/decoder/sequentialDecoders.py
spiro/dtdg/models/decoder/simpleDecoders.py
spiro/dtdg/models/decoder/tf/__init__.py
spiro/dtdg/models/decoder/tf/sequentialDecoder/__init__.py
spiro/dtdg/models/decoder/tf/sequentialDecoder/baseModel.py
spiro/dtdg/models/decoder/tf/sequentialDecoder/implicitTimeModels.py
spiro/dtdg/models/decoder/tf/simpleDecoder.py
spiro/dtdg/models/decoder/torch/__init__.py
spiro/dtdg/models/decoder/torch/sequentialDecoder/__init__.py
spiro/dtdg/models/decoder/torch/sequentialDecoder/implicitTimeModels.py
spiro/dtdg/models/decoder/torch/simpleDecoder.py
spiro/dtdg/models/encoder/implicitTimeEncoder/staticGraphEncoder.py
spiro/dtdg/models/encoder/implicitTimeEncoder/tf/dysat_gat.py
spiro/dtdg/types.py
spirograph-0.0.0.dist-info/LICENSE
spirograph-0.0.0.dist-info/WHEEL
spirograph-0.0.0.dist-info/METADATA
spirograph-0.0.0.dist-info/RECORD
